mux_python/__init__.py
mux_python/api_client.py
mux_python/configuration.py
mux_python/exceptions.py
mux_python/rest.py
mux_python/api/__init__.py
mux_python/api/annotations_api.py
mux_python/api/assets_api.py
mux_python/api/delivery_usage_api.py
mux_python/api/dimensions_api.py
mux_python/api/direct_uploads_api.py
mux_python/api/drm_configurations_api.py
mux_python/api/errors_api.py
mux_python/api/exports_api.py
mux_python/api/filters_api.py
mux_python/api/incidents_api.py
mux_python/api/live_streams_api.py
mux_python/api/metrics_api.py
mux_python/api/monitoring_api.py
mux_python/api/playback_id_api.py
mux_python/api/playback_restrictions_api.py
mux_python/api/real_time_api.py
mux_python/api/signing_keys_api.py
mux_python/api/spaces_api.py
mux_python/api/transcription_vocabularies_api.py
mux_python/api/url_signing_keys_api.py
mux_python/api/video_views_api.py
mux_python/api/web_inputs_api.py
mux_python/models/__init__.py
mux_python/models/abridged_video_view.py
mux_python/models/annotation.py
mux_python/models/annotation_input.py
mux_python/models/annotation_response.py
mux_python/models/asset.py
mux_python/models/asset_errors.py
mux_python/models/asset_generated_subtitle_settings.py
mux_python/models/asset_master.py
mux_python/models/asset_metadata.py
mux_python/models/asset_non_standard_input_reasons.py
mux_python/models/asset_progress.py
mux_python/models/asset_recording_times.py
mux_python/models/asset_response.py
mux_python/models/asset_static_renditions.py
mux_python/models/asset_static_renditions_files.py
mux_python/models/breakdown_value.py
mux_python/models/broadcast.py
mux_python/models/broadcast_layout.py
mux_python/models/broadcast_resolution.py
mux_python/models/broadcast_response.py
mux_python/models/broadcast_status.py
mux_python/models/create_asset_request.py
mux_python/models/create_broadcast_request.py
mux_python/models/create_live_stream_request.py
mux_python/models/create_playback_id_request.py
mux_python/models/create_playback_id_response.py
mux_python-5.1.2.dist-info/licenses/LICENSE
mux_python-5.1.2.dist-info/METADATA
mux_python-5.1.2.dist-info/WHEEL
mux_python-5.1.2.dist-info/top_level.txt
mux_python-5.1.2.dist-info/RECORD
