Metadata-Version: 2.4
Name: mux_python
Version: 5.1.2
Summary: Mux API
Home-page: https://github.com/muxinc/mux-python
Author: Mux DevEx
Author-email: devex@mux.com
License: MIT
Keywords: OpenAPI,OpenAPI-Generator,Mux API
License-File: LICENSE
Requires-Dist: urllib3>=1.25.3
Requires-Dist: six>=1.10
Requires-Dist: python-dateutil
Dynamic: author
Dynamic: author-email
Dynamic: description
Dynamic: description-content-type
Dynamic: home-page
Dynamic: keywords
Dynamic: license
Dynamic: license-file
Dynamic: requires-dist
Dynamic: summary
